mkdocs_exclude_plugin/__init__.py
mkdocs_exclude_plugin/plugin.py
mkdocs_minyilife_exclude_plugin/__init__.py
mkdocs_minyilife_exclude_plugin/plugin.py
mkdocs_minyilife_ruby_plugin/__init__.py
mkdocs_minyilife_ruby_plugin/plugin.py
mkdocs_minyilife_tags_plugin/__init__.py
mkdocs_minyilife_tags_plugin/plugin.py
mkdocs_ruby_plugin/__init__.py
mkdocs_ruby_plugin/plugin.py
mkdocs_tags_plugin/__init__.py
mkdocs_tags_plugin/plugin.py
mkdocs_minyilife_plugin-0.0.6.dist-info/LICENSE
mkdocs_minyilife_plugin-0.0.6.dist-info/METADATA
mkdocs_minyilife_plugin-0.0.6.dist-info/WHEEL
mkdocs_minyilife_plugin-0.0.6.dist-info/entry_points.txt
mkdocs_minyilife_plugin-0.0.6.dist-info/top_level.txt
mkdocs_minyilife_plugin-0.0.6.dist-info/RECORD
