Metadata-Version: 2.1
Name: mkdocs-minyilife-plugin
Version: 0.0.6
Summary: An MkDocs plugin for www.lesliezhu.com blog.
Home-page: https://github.com/lesliezhu/mkdocs-minyilife-plugin
Author: Leslie Zhu
Author-email: pythonisland@gmail.com
License: Apache-2.0
Keywords: mkdocs minyilife plugin
Platform: UNKNOWN
Requires-Python: >=3.9
License-File: LICENSE
Requires-Dist: mkdocs>=1.4.1
